setup.cfg
setup.py
python_slimta_celeryqueue.egg-info/PKG-INFO
python_slimta_celeryqueue.egg-info/SOURCES.txt
python_slimta_celeryqueue.egg-info/dependency_links.txt
python_slimta_celeryqueue.egg-info/namespace_packages.txt
python_slimta_celeryqueue.egg-info/requires.txt
python_slimta_celeryqueue.egg-info/top_level.txt
slimta/__init__.py
slimta/celeryqueue/__init__.py
test/test_slimta_celeryqueue.py